orthograph/__init__.py
orthograph-0.0.0.dist-info/METADATA
orthograph-0.0.0.dist-info/WHEEL
orthograph-0.0.0.dist-info/top_level.txt
orthograph-0.0.0.dist-info/RECORD
